stackhpc_inspector_plugins/__init__.py
stackhpc_inspector_plugins/conf.py
stackhpc_inspector_plugins/utils.py
stackhpc_inspector_plugins/plugins/__init__.py
stackhpc_inspector_plugins/plugins/base_physnet.py
stackhpc_inspector_plugins/plugins/hpcdirect_physnet.py
stackhpc_inspector_plugins/plugins/ib_physnet.py
stackhpc_inspector_plugins/plugins/system_name_llc.py
stackhpc_inspector_plugins/plugins/system_name_physnet.py
stackhpc_inspector_plugins/tests/__init__.py
stackhpc_inspector_plugins/tests/unit/__init__.py
stackhpc_inspector_plugins/tests/unit/test_plugins_base_physnet.py
stackhpc_inspector_plugins/tests/unit/test_plugins_ib_physnet.py
stackhpc_inspector_plugins/tests/unit/test_plugins_system_name_llc.py
stackhpc_inspector_plugins/tests/unit/test_plugins_system_name_physnet.py
stackhpc_inspector_plugins/tests/unit/test_utils.py
stackhpc_inspector_plugins-1.1.1.dist-info/DESCRIPTION.rst
stackhpc_inspector_plugins-1.1.1.dist-info/METADATA
stackhpc_inspector_plugins-1.1.1.dist-info/RECORD
stackhpc_inspector_plugins-1.1.1.dist-info/WHEEL
stackhpc_inspector_plugins-1.1.1.dist-info/entry_points.txt
stackhpc_inspector_plugins-1.1.1.dist-info/metadata.json
stackhpc_inspector_plugins-1.1.1.dist-info/pbr.json
stackhpc_inspector_plugins-1.1.1.dist-info/top_level.txt
