Metadata-Version: 2.0
Name: stackhpc-inspector-plugins
Version: 1.1.1
Summary: StackHPC plugins for OpenStack ironic inspector
Home-page: https://github.com/stackhpc/stackhpc-inspector-plugins
Author: StackHPC Ltd
Author-email: mark@stackhpc.com
License: Apache-2
Platform: UNKNOWN
Classifier: Environment :: Console
Classifier: Environment :: OpenStack
Classifier: Intended Audience :: System Administrators
Classifier: Intended Audience :: Information Technology
Classifier: License :: OSI Approved :: Apache Software License
Classifier: Operating System :: OS Independent
Classifier: Programming Language :: Python
Classifier: Programming Language :: Python :: 2
Requires-Dist: pbr (!=2.1.0,>=2.0.0)
